fiveg_core_common_schemas/AccessType.py
fiveg_core_common_schemas/AllowedNssai.py
fiveg_core_common_schemas/AllowedSNssai.py
fiveg_core_common_schemas/Ambr.py
fiveg_core_common_schemas/AmfId.py
fiveg_core_common_schemas/AmfName.py
fiveg_core_common_schemas/AmfRegionId.py
fiveg_core_common_schemas/AmfSetId.py
fiveg_core_common_schemas/Area.py
fiveg_core_common_schemas/AreaCode.py
fiveg_core_common_schemas/Arp.py
fiveg_core_common_schemas/ArpPriorityLevel.py
fiveg_core_common_schemas/Autn.py
fiveg_core_common_schemas/Auts.py
fiveg_core_common_schemas/BitRate.py
fiveg_core_common_schemas/CagId.py
fiveg_core_common_schemas/ConfiguredSnssai.py
fiveg_core_common_schemas/CoreNetworkType.py
fiveg_core_common_schemas/CorrelationID.py
fiveg_core_common_schemas/DateTime.py
fiveg_core_common_schemas/DiameterIdentity.py
fiveg_core_common_schemas/Dnn.py
fiveg_core_common_schemas/ENbId.py
fiveg_core_common_schemas/EbiArpMapping.py
fiveg_core_common_schemas/Ecgi.py
fiveg_core_common_schemas/EpsBearerId.py
fiveg_core_common_schemas/EutraCellId.py
fiveg_core_common_schemas/EutraLocation.py
fiveg_core_common_schemas/Fqdn.py
fiveg_core_common_schemas/GNbId.py
fiveg_core_common_schemas/Gci.py
fiveg_core_common_schemas/Gli.py
fiveg_core_common_schemas/GlobalRanNodeId.py
fiveg_core_common_schemas/Gpsi.py
fiveg_core_common_schemas/GroupId.py
fiveg_core_common_schemas/Guami.py
fiveg_core_common_schemas/HfcNId.py
fiveg_core_common_schemas/HfcNodeId.py
fiveg_core_common_schemas/Ipv4Addr.py
fiveg_core_common_schemas/Ipv6Addr.py
fiveg_core_common_schemas/Ipv6Prefix.py
fiveg_core_common_schemas/LineType.py
fiveg_core_common_schemas/Mcc.py
fiveg_core_common_schemas/Mnc.py
fiveg_core_common_schemas/N1MessageClass.py
fiveg_core_common_schemas/N2InformationClass.py
fiveg_core_common_schemas/N3IwfId.py
fiveg_core_common_schemas/N3gaLocation.py
fiveg_core_common_schemas/Ncgi.py
fiveg_core_common_schemas/NetworkId.py
fiveg_core_common_schemas/NfGroupId.py
fiveg_core_common_schemas/NfInstanceId.py
5g_core_common_schemas-1.0.9.dist-info/LICENSE.md
5g_core_common_schemas-1.0.9.dist-info/METADATA
5g_core_common_schemas-1.0.9.dist-info/WHEEL
5g_core_common_schemas-1.0.9.dist-info/top_level.txt
5g_core_common_schemas-1.0.9.dist-info/RECORD
