Metadata-Version: 2.1
Name: 5g-core-common-schemas
Version: 1.0.9
Summary: Common Schemas used in 5G core
Author-email: Guillaume Belanger <guillaume.belanger27@gmail.com>
Project-URL: Homepage, https://github.com/gruyaume/5g-core-common-schemas
Keywords: 5G,Core,Network
Classifier: License :: OSI Approved :: Apache Software License
Classifier: Programming Language :: Python
Classifier: Programming Language :: Python :: 3
Requires-Python: >=3.8
License-File: LICENSE.md
Requires-Dist: feedparser (>=5.2.0)
Requires-Dist: html2text
Requires-Dist: pydantic
Requires-Dist: tomli ; python_version < "3.11"
